{
  "$schema": "https://developer.microsoft.com/json-schemas/spfx-build/package-solution.schema.json",
  "solution": {
    "name": "sp-fx-app-customizer-client-side-solution",
    "id": "f44bd91d-81e3-4504-af92-73c178d77157",
    "version": "1.0.0.0",
    "includeClientSideAssets": true,
    "isDomainIsolated": false,
    "developer": {
      "name": "",
      "websiteUrl": "",
      "privacyUrl": "",
      "termsOfUseUrl": "",
      "mpnId": ""
    },
    "features": [
      {
        "title": "Application Extension - Deployment of custom action.",
        "description": "Deploys a custom action with ClientSideComponentId association",
        "id": "aaf9443b-5fcb-403d-a618-b6987181a482",
        "version": "1.0.0.0",
        "assets": {
          "elementManifests": [
            "elements.xml",
            "ClientSideInstance.xml"
          ]
        }
      }
    ]
  },
  "paths": {
    "zippedPackage": "solution/sp-fx-app-customizer.sppkg"
  }
}
